goeiedag/__init__.py
goeiedag/_graph.py
goeiedag/_model.py
goeiedag/_ninja_builder.py
goeieDAG-0.0.2.dist-info/LICENSE
goeieDAG-0.0.2.dist-info/METADATA
goeieDAG-0.0.2.dist-info/WHEEL
goeieDAG-0.0.2.dist-info/top_level.txt
goeieDAG-0.0.2.dist-info/RECORD
