Metadata-Version: 2.1
Name: goeieDAG
Version: 0.0.2
Summary: Task crunching with Ninja or Make
Home-page: https://github.com/mcejp/goeieDAG
License: MIT
Keywords: dag,make,makefile,ninja
Classifier: Development Status :: 3 - Alpha
Classifier: Environment :: Console
Classifier: License :: OSI Approved :: MIT License
Classifier: Programming Language :: Python :: 3
Classifier: Programming Language :: Python :: 3.9
Requires-Python: >=3.9
License-File: LICENSE
Requires-Dist: ninja
Provides-Extra: dev
Requires-Dist: black ; extra == 'dev'
Requires-Dist: mypy ; extra == 'dev'
